pybsky/__init__.py
pybsky/client.py
pybsky/core/__init__.py
pybsky/core/configs.py
pybsky/core/exceptions.py
pybsky/core/user_agents.py
pybsky/core/utils.py
pybsky/mixins/__init__.py
pybsky/mixins/base.py
pybsky/mixins/feed.py
pybsky/mixins/graph.py
pybsky/mixins/login.py
pybsky/mixins/notification.py
pybsky/mixins/post.py
pybsky/mixins/profile.py
pybsky/mixins/repo.py
pybsky/mixins/server.py
pybsky-0.0.20.dist-info/LICENSE
pybsky-0.0.20.dist-info/METADATA
pybsky-0.0.20.dist-info/WHEEL
pybsky-0.0.20.dist-info/top_level.txt
pybsky-0.0.20.dist-info/RECORD
