Metadata-Version: 2.1
Name: pybsky
Version: 0.0.20
Summary: Python Client for bsky social media
Author-email: Mohammadreza softrebel <sh.mohammad66@yahoo.com>, Mahdi Ovan <mahdi.ovan@yahoo.com>
Project-URL: Homepage, https://github.com/softrebel/pybsky
Project-URL: BugTracker, https://github.com/softrebel/pybsky/issues
Project-URL: Repository, https://github.com/softrebel/pybsky
Classifier: Programming Language :: Python :: 3
Classifier: License :: OSI Approved :: MIT License
Classifier: Operating System :: OS Independent
Requires-Python: >=3.10
License-File: LICENSE
Requires-Dist: requests (==2.31.0)
